caskada.py
caskada-2.2.0.dist-info/METADATA
caskada-2.2.0.dist-info/WHEEL
caskada-2.2.0.dist-info/top_level.txt
caskada-2.2.0.dist-info/RECORD
