Metadata-Version: 2.4
Name: caskada
Version: 2.2.0
Summary: Minimalist AI framework in 300 Lines. Enable LLMs to Program Themselves.
Home-page: https://skada.ai/caskada/
Author: Victor Duarte
License: MPL-2.0
Classifier: License :: OSI Approved :: Mozilla Public License 2.0 (MPL 2.0)
Dynamic: author
Dynamic: classifier
Dynamic: description
Dynamic: description-content-type
Dynamic: home-page
Dynamic: license
Dynamic: summary
